{
    "ret": "0",
    "sid": "66758179603e565793cab067f4f77cc6",
    "runrecord":
    {
        "endtime": 1539089975,
        "uid": 87808183,
        "fid": 249654660,
        "sampleinterval": 5,
        "second": 475,
        "altitude": [50.91, 50.66, 51.02, 50.98, 51.51, 51.12, 51.27, 50.9, 51.08, 50.98, 51.3, 51.53, 51.89, 51.11, 50.89, 51.25, 50.94, 50.73, 51.18, 50.72, 50.97, 51.59, 51.04, 51.15, 51.28, 51.03, 50.63, 50.56, 50.8, 50.6, 50.65, 50.79, 50.65, 50.47, 50.88, 50.66, 50.63, 50.19, 50.37, 50.59, 50.7, 51, 50.87, 50.83, 50.83, 50.91, 50.74, 50.94, 50.73, 50.63, 50.94, 50.68, 50.81, 50.72, 50.74, 50.83, 51.19, 50.62, 50.75, 50.51, 50.8, 50.7, 50.99, 50.64, 50.71, 50.5, 50.73, 50.9, 50.52, 50.98, 50.7, 50.58, 50.66, 50.92, 50.84, 50.67, 50.17, 50.48, 49.54, 50.34, 50.17, 50.12, 51.26, 50.32, 50.36, 50.55, 50.5, 50.37, 50.71, 50.36, 50.35, 50.99, 51.36, 50.28, 50.39, 50.39],
        "nodeattach": [
            ["39985549", "116307176", "55"]
        ],
        "fraud": 0,
        "type": 1,
        "city": "北京",
        "private": 0,
        "pause": [],
        "meter": 1718,
        "wgs": 1,
        "heartrate": [],
        "province": "北京市",
        "stepcontent": [
            [2, 2.2],
            [16, 17.6],
            [14, 15.4],
            [15, 16.5],
            [15, 16.5],
            [16, 17.6],
            [15, 16.5],
            [19, 15.96],
            [16, 13.44],
            [16, 13.44],
            [14, 11.76],
            [15, 12.6],
            [14, 15.26],
            [14, 15.26],
            [14, 15.26],
            [13, 14.17],
            [14, 15.26],
            [13, 14.17],
            [14, 15.26],
            [13, 14.17],
            [18, 19.62],
            [19, 20.71],
            [14, 12.74],
            [14, 12.74],
            [14, 12.74],
            [13, 11.83],
            [14, 12.74],
            [14, 17.22],
            [13, 15.99],
            [14, 17.22],
            [13, 15.99],
            [14, 17.22],
            [15, 17.1],
            [16, 18.24],
            [14, 15.96],
            [14, 15.96],
            [13, 14.82],
            [13, 14.56],
            [13, 14.56],
            [13, 14.56],
            [14, 15.68],
            [13, 14.56],
            [13, 16.12],
            [16, 19.84],
            [14, 17.36],
            [16, 19.84],
            [13, 16.12],
            [17, 18.02],
            [13, 13.78],
            [14, 14.84],
            [14, 14.84],
            [14, 14.84],
            [17, 20.23],
            [14, 16.66],
            [13, 15.47],
            [14, 16.66],
            [13, 15.47],
            [13, 17.42],
            [15, 20.1],
            [13, 17.42],
            [19, 25.46],
            [13, 17.42],
            [13, 11.31],
            [13, 11.31],
            [14, 12.18],
            [13, 11.31],
            [13, 11.31],
            [14, 12.18],
            [13, 11.31],
            [13, 11.31],
            [16, 13.92],
            [13, 11.31],
            [14, 15.4],
            [19, 20.9],
            [18, 19.8],
            [13, 14.3],
            [14, 15.4],
            [13, 13.91],
            [13, 13.91],
            [14, 14.98],
            [13, 13.91],
            [13, 13.91],
            [13, 16.25],
            [16, 20.0],
            [14, 17.5],
            [15, 18.75],
            [14, 17.5],
            [18, 21.78],
            [16, 19.36],
            [14, 16.94],
            [14, 16.94],
            [15, 18.15],
            [14, 14.56],
            [14, 14.56],
            [13, 13.52],
            [0, 0.0]
        ],
        "daka": 290,
        "stepremark": [
            [0, 1, 19]
        ],
        "starttime": 1539089496,
        "status": 1,
        "url": "http://wap.thejoyrun.com/po_87808183_249654660.html",
        "content": [
            [39986541, 116306621],
            [39986541, 116306621],
            [39986541, 116306621],
            [39986417, 116306644],
            [39986189, 116306666],
            [39986084, 116306656],
            [39985904, 116306679],
            [39985796, 116306809],
            [39985682, 116307077],
            [39985665, 116307284],
            [39985710, 116307558],
            [39985793, 116307682],
            [39986057, 116307665],
            [39986228, 116307640],
            [39986473, 116307675],
            [39986642, 116307625],
            [39986854, 116307490],
            [39986980, 116307408],
            [39987005, 116307121],
            [39986977, 116306981],
            [39986962, 116306838],
            [39986859, 116306742],
            [39986674, 116306695],
            [39986551, 116306608],
            [39986319, 116306608],
            [39986199, 116306641],
            [39986027, 116306670],
            [39985898, 116306653],
            [39985750, 116306675],
            [39985658, 116306841],
            [39985633, 116307092],
            [39985634, 116307291],
            [39985739, 116307523],
            [39985794, 116307652],
            [39985914, 116307713],
            [39986053, 116307688],
            [39986274, 116307693],
            [39986407, 116307671],
            [39986579, 116307622],
            [39986708, 116307595],
            [39986862, 116307553],
            [39987029, 116307359],
            [39987068, 116307196],
            [39987042, 116306947],
            [39986993, 116306816],
            [39986872, 116306637],
            [39986724, 116306617],
            [39986530, 116306553],
            [39986411, 116306550],
            [39986209, 116306606],
            [39986041, 116306625],
            [39985873, 116306587],
            [39985733, 116306633],
            [39985608, 116306802],
            [39985529, 116306935],
            [39985549, 116307176],
            [39985763, 116307484],
            [39985857, 116307609],
            [39985999, 116307668],
            [39986074, 116307754],
            [39986200, 116307718],
            [39986327, 116307701],
            [39986535, 116307716],
            [39986671, 116307713],
            [39986837, 116307614],
            [39986960, 116307435],
            [39987042, 116307211],
            [39987043, 116307049],
            [39987005, 116306867],
            [39986895, 116306760],
            [39986727, 116306595],
            [39986578, 116306575],
            [39986390, 116306591],
            [39986257, 116306604],
            [39986050, 116306648],
            [39985931, 116306621],
            [39985746, 116306669],
            [39985633, 116306783],
            [39985597, 116307070],
            [39985615, 116307271],
            [39985697, 116307474],
            [39985767, 116307615],
            [39985974, 116307729],
            [39986075, 116307758],
            [39986238, 116307744],
            [39986379, 116307732],
            [39986616, 116307658],
            [39986749, 116307631],
            [39986930, 116307498],
            [39987013, 116307353],
            [39987031, 116307085],
            [39987026, 116306925],
            [39986948, 116306802],
            [39986809, 116306668],
            [39986672, 116306606],
            [39986672, 116306606]
        ],
        "timeConflict": 0,
        "node": [
            ["1000", "274"]
        ],
        "source": "",
        "totalsteps": 1351,
        "postRunId": 239281538
    },
    "lasttime": 1539352089,
    "msg": "成功"
}